{
  "Clash of Knights": "Ritarien taisto",
  "Night of the Moth": "Koiden yo",
  "The Brave & The Beautiful": "Kauniit ja urheat",
  "Chess Event": "Shakkitapahtuma",
  "Covenant Quest": "Kovenanttiseikkailu",
  "Special Guest Event": "Erikoisvierastapahtuma",
  "Beowulf's Challenge": "Beowulfin haaste",
  "Starfall Circus": "Sirkus Tahtisade",
  "Challenge Festival I": "Haastefestivaali I",
  "Challenge Festival II": "Haastefestivaali II",
  "Sanctuary of Gargoyles": "Gargoilien pyhakko",
  "Return to Sanctuary": "Paluu pyhakkoon",
  "Carnival of Gods": "Jumalten karnevaali",
  "Mighty Pets": "Mahtilemmikit",
  "Secrets of the Opera": "Oopperan salaisuudet",
  "Slayers of Fell Shadows": "Synkkien varjojen surmaajat",
  "League of Villains": "Konnien liitto",
  "Tower of Magic": "Taikatorni",
  "Ninja Tower": "Ninjatorni",
  "Owl Tower": "Pollotorni",
  "Tower of Styx": "Styksin torni",
  "Treasure Quest": "Aarreseikkailu"
}