{
  "Underwild Family": "언더와일드 패밀리",
  "Underwild": "언더와일드",
  "Abyss Hunter Family": "심연의 헌터 패밀리",
  "Abyss Hunter": "심연의 헌터",
  "Alfheim Realm": "알프하임 왕국",
  "Alfheim": "알프하임",
  "Asgard Realm": "아스가르드 왕국",
  "Asgard": "아스가르드",
  "Astral Demons": "아스트랄 악귀",
  "Astral Dwarfs Family": "아스트랄 드워프 패밀리",
  "Astral Dwarfs": "아스트랄 드워프",
  "Astral Elves Family": "아스트랄 엘프 패밀리",
  "Astral Elves": "아스트랄 엘프",
  "Atlantis Family": "아틀란티스 패밀리",
  "Atlantis": "아틀란티스",
  "Bard Family": "시인 패밀리",
  "Bard": "시인",
  "Beach Party Family": "해변 파티 패밀리",
  "Beach Party": "해변 파티",
  "Bear Family": "곰 패밀리",
  "Bear": "곰",
  "Beauty and the Beast Family": "미녀와 야수 패밀리",
  "Beauty and the Beast": "미녀와 야수",
  "Beowulf Family": "베오울프 패밀리",
  "Beowulf": "베오울프",
  "Champions Family": "챔피언 패밀리",
  "Champions": "챔피언",
  "Starfall Family": "스타폴 패밀리",
  "Starfall": "스타폴",
  "Classic Family": "클래식 패밀리",
  "Classic": "클래식",
  "Construct Family": "수호물 패밀리",
  "Construct": "수호물",
  "Cultist Family": "숭배자 패밀리",
  "Cultist": "숭배자",
  "Cupid Family": "큐피드 패밀리",
  "Cupid": "큐피드",
  "Springvale Family": "스프링베일 패밀리",
  "Springvale": "스프링베일",
  "Grimforest Family": "음험한 숲 패밀리",
  "Grimforest": "음험한 숲",
  "Woodland Faun Family": "숲속 파우누스 패밀리",
  "Woodland Faun": "숲속 파우누스",
  "Fleur de Sang Family": "플뢰르 드 상 패밀리",
  "Fleur de Sang": "플뢰르 드 상",
  "Forsaken Family": "버림받은 패밀리",
  "Forsaken": "버림받은",
  "Fortune Dancer Family": "행운 댄서 패밀리",
  "Fortune": "행운",
  "Fox Family": "여우 패밀리",
  "Fox": "여우",
  "Gargoyle Family": "가고일 패밀리",
  "Gargoyle": "가고일",
  "Garrison Guard Family": "수비대 경비병 패밀리",
  "Garrison Guard": "수비대 경비병",
  "Goblin Family": "고블린 패밀리",
  "Goblin": "고블린",
  "Guardian Family": "수호자 패밀리",
  "Guardian": "수호자",
  "Morlovia Family": "몰로비아 패밀리",
  "Morlovia": "몰로비아",
  "Helheim Realm": "헬하임 왕국",
  "Helheim": "헬하임",
  "Legends {0} Family": "전설 {0} 패밀리",
  "Legends {0}": "전설 {0}",
  "The Institute Family": "근본 패밀리",
  "The Institute": "근본",
  "Investigator Family": "조사원 패밀리",
  "Investigator": "조사원",
  "Sakura Family": "사쿠라 패밀리",
  "Sakura": "사쿠라",
  "Jotunheim Realm": "요툰하임 왕국",
  "Jotunheim": "요툰하임",
  "Journey Family": "여행 패밀리",
  "Journey": "여행",
  "Jungle Hunter Family": "정글 헌터 패밀리",
  "Jungle Hunter": "정글 헌터",
  "Kalevala Family": "칼레발라 패밀리",
  "Kalevala": "칼레발라",
  "Kingdom Family": "왕국 패밀리",
  "Kingdom": "왕국",
  "Avalon Family": "아발론 패밀리",
  "Avalon": "아발론",
  "Lagoon Family": "라군 패밀리",
  "Lagoon": "라군",
  "Magic Family": "매직 패밀리",
  "Magic": "매직",
  "Magic Carpet Family": "마법 양탄자 패밀리",
  "Magic Carpet": "마법 양탄자",
  "Mahayoddha Family": "마헤이요다 패밀리",
  "Mahayoddha": "마헤이요다",
  "Masked God Family": "가면 쓴 신 패밀리",
  "Masked God": "가면 쓴 신",
  "Midgard Realm": "미드가르드 왕국",
  "Midgard": "미드가르드",
  "Mighty Pet Family": "강력한 펫 패밀리",
  "Mighty Pet": "강력한 펫",
  "Mimic Family": "미믹 패밀리",
  "Mimic": "미믹",
  "Moon Family": "달 패밀리",
  "Moon": "달",
  "Moth Family": "나방 패밀리",
  "Moth": "나방",
  "Musketeer Family": "총사 패밀리",
  "Musketeer": "총사",
  "Muspelheim Realm": "무스펠하임 왕국",
  "Muspelheim": "무스펠하임",
  "Myrkheim": "미르하임",
  "Mystery Family": "미스테리 패밀리",
  "Mystery": "미스테리",
  "Nidavellir Realm": "니다벨리르 왕국",
  "Nidavellir": "니다벨리르",
  "Niflheim Realm": "니플하임 왕국",
  "Niflheim": "니플하임",
  "Ninja Family": "닌자 패밀리",
  "Ninja": "닌자",
  "Opera Family": "오페라 패밀리",
  "Opera": "오페라",
  "Outlaws of Liangshan Family": "량산의 무법자 패밀리",
  "Outlaws of Liangshan": "량산의 무법자",
  "Owl Family": "올빼미 패밀리",
  "Owl": "올빼미",
  "Pirate Family": "해적 패밀리",
  "Pirate": "해적",
  "Plains Hunter Family": "몬스터 사냥꾼 가족",
  "Plains Hunter": "몬스터 사냥꾼",
  "Raven Family": "까마귀 패밀리",
  "Raven": "까마귀",
  "Adventurous Rodent Family": "모험적인 설치류 패밀리",
  "Adventurous Rodent": "모험적인 설치류",
  "Ronin Family": "로닌 패밀리",
  "Ronin": "로닌",
  "Sand Empire Family": "모래 제국 패밀리",
  "Sand Empire": "모래 제국",
  "Shady Scoundrel Family": "어두운 악당 패밀리",
  "Shady Scoundrel": "어두운 악당",
  "Slayer Family": "처단자 패밀리",
  "Slayer": "처단자",
  "Slime Family": "슬라임 패밀리",
  "Slime": "슬라임",
  "Stag Family": "사슴 패밀리",
  "Stag": "사슴",
  "Styx Family": "스틱스 패밀리",
  "Styx": "스틱스",
  "Sun Family": "태양 패밀리",
  "Sun": "태양",
  "Super Elemental Family": "슈퍼 엘리멘탈 패밀리",
  "Super Elemental": "슈퍼 엘리멘탈",
  "Svartalfheim Realm": "스바르탈프하임 왕국",
  "Svartalfheim": "스바르탈프하임",
  "Nightmares of Atlantis Family": "아틀란티스의 악몽 패밀리",
  "Nightmares of Atlantis": "아틀란티스의 악몽",
  "Defenders of Atlantis Family": "아틀란티스의 방어병 패밀리",
  "Defenders of Atlantis": "아틀란티스의 방어병",
  "Titan Hunter Family": "타이탄 사냥꾼 패밀리",
  "Titan Hunter": "타이탄 사냥꾼",
  "Vanaheim Realm": "바나하임 왕국",
  "Vanaheim": "바나하임",
  "Valiant Vegetable Family": "용맹한 채소 패밀리",
  "Valiant Vegetable": "용맹한 채소",
  "Villain Family": "빌런 패밀리",
  "Villain": "빌런",
  "Wild Cat Family": "들고양이 패밀리",
  "Wild Cat": "들고양이",
  "Winter Family": "윈터 패밀리",
  "Winter": "윈터",
  "Wolf Family": "늑대 패밀리",
  "Wolf": "늑대",
  "Wonderland Family": "원더랜드 패밀리",
  "Wonderland": "원더랜드",
  "Lunar Year Family": "음력 패밀리",
  "Lunar Year": "음력"
}