{
  "Birthday Summon": "Chiamata del compleanno",
  "Alliance Quest Summon": "Chiamata dell'Impresa dell'Alleanza",
  "Ancient Dragon Summon": "Chiamata dei draghi antichi",
  "Ascension Summon": "Chiamata dell'ascensione",
  "Instant Power": "Potere istantaneo",
  "Astral Summon": "Chiamata astrale",
  "Black Friday Summon": "Chiamata del Black Friday",
  "Event Summon": "Chiamata evento",
  "Costume Summon": "Chiamata Costume",
  "Covenant Summon": "Chiamata del Patto",
  "Daily Summon": "Chiamata giornaliera",
  "Elemental Dragon Summon": "Chiamata dei draghi elementale",
  "Elemental Summon": "Chiamata elementale",
  "Legendary Dragon Summon": "Chiamata dei draghi leggendaria",
  "Epic Hero Summon": "Chiamata Eroe epico",
  "Epic Troop Summon": "Chiamata truppa epica",
  "Goblin Summon": "Chiamata dei goblin",
  "Harvest Summon": "Chiamata del raccolto",
  "Hero League Summon": "Chiamata della Lega degli Eroi",
  "Legendary Troop Summon": "Chiamata truppa leggendaria",
  "Legends Summon": "Chiamata delle Leggende",
  "Aether Summon": "Chiamata delle Eteree",
  "Summon Updated": "Chiamata aggiornata",
  "3 Kingdoms Summon": "Chiamata dei 3 Regni",
  "Mimic Summon": "Chiamata del mimic",
  "Monster Island Summon": "Chiamata dell'Isola dei mostri",
  "Pick Up Summon": "Chiamata di recupero",
  "Atlantis Summon": "Chiamata di Atlantide",
  "Valhalla Summon": "Chiamata del Valhalla",
  "Underwild Summon": "Chiamata delle Profondita",
  "Dunes Summon": "Chiamata delle Dune",
  "Seasonal Summon": "Chiamata stagionale",
  "Sanguine Summon": "Chiamata sanguigna",
  "Shadow Summon": "Chiamata delle ombre",
  "Silver Summon": "Chiamata argentea",
  "Solstice Summon": "Chiamata del solstizio",
  "Spring Summon": "Chiamata di primavera",
  "Untold Tales": "Storie non raccontate",
  "Super Elemental Summon": "Chiamata dei Super elementi",
  "Temple Summon": "Chiamata del Tempio",
  "Tower Summon": "Chiamata della Torre",
  "Tower Troop Summon": "Chiamata delle truppe della Torre",
  "Untold Tales Summon": "Chiamata delle Storie non raccontate",
  "Mysteries of the Deep": "Misteri degli abissi",
  "Treasures of Flame and Frost": "Tesori della Fiamma e del Gelo",
  "Wilderness Summon": "Chiamata della Selva"
}