{
  "Ancient Underroot": "Gammel Underrot",
  "Find Training Items": "Finn treningselementer",
  "Astral Plane": "Astralsletten",
  "Find Battle Items": "Finn kampelementer",
  "Find Battle Items II": "Finn kampelementer II",
  "Beach Party": "Strandfest",
  "Beowulf's Challenge": "Beowulfs utfordring",
  "Clash of Knights": "Riddernes kamp",
  "Starfall Circus": "Stjerneskudd-sirkus",
  "Trials of Decimation": "Prøvelser i desimering",
  "Trials of Fortitude": "Prøvelser i heltemot",
  "Trials of Serenity": "Prøvelser i sinnsro",
  "Trials of Justice": "Prøvelser i rettferdighet",
  "Trials of Mysticism": "Prøvelser i mystikk",
  "Trials of Nature": "Prøvelser i natur",
  "Trials of Piety": "Prøvelser i fromhet",
  "Trials of Shadows": "Prøvelser i skygger",
  "Trials of Strength": "Prøvelser i styrke",
  "Trials of Survival": "Prøvelser i overlevelse",
  "The Masquerade": "Maskerade",
  "Covenant Quest": "Paktoppdrag",
  "Find Crafting Materials": "Finn produksjonsmaterialer",
  "Find Crafting Materials II": "Finn produksjonsmaterialer II",
  "Night of Items": "Gjenstandskveld",
  "Dragon Cave": "Dragegrotte",
  "Rescue Dragonlings": "Redd smadrager",
  "River of Resources": "Ressurselv",
  "Sapphire Cavern": "Safirhule",
  "Rainbow Cavern": "Regnbuehule",
  "Jewelry Cavern": "Juvelhule",
  "Jade Cavern": "Jadehule",
  "Amethyst Cavern": "Ametysthule",
  "Ruby Cavern": "Rubinhule",
  "Topaz Cavern": "Topashule",
  "Legendary Dragon Quest": "Legendarisk drageoppdrag",
  "Scroll Cavern": "Pergamenthule",
  "Frostmarch": "Frostgrensen",
  "Farholme Pass": "Farholme-passet",
  "Shrikewood": "Skrikeskogen",
  "Morlovia": "Morlovia",
  "Mount Umber": "Umber-fjellet",
  "Shiloh Desert": "Shiloh-ørkenen",
  "Challenge Festival I": "Utfordringsfestival I",
  "Challenge Festival II": "Utfordringsfestival II",
  "Gather Food": "Samle mat",
  "Sanctuary of Gargoyles": "Griffenes tilfluktssted",
  "Return to Sanctuary": "Returner til tilfluktssted",
  "Collect Gems": "Samle juveler",
  "Collect Gems II": "Samle juveler II",
  "Goblin Village": "Goblinlandsby",
  "Special Guest Event": "Spesiell gjest-hendelse",
  "Return to Morlovia": "Tilbake til Morlovia",
  "The Sanguine Feast": "Det optimistiske festmaltidet",
  "Tavern of Legends": "Legendenes kro",
  "Mine Iron": "Utvinn jern",
  "Kalevala": "Kalevala",
  "Mirages of Omega": "Omegas luftspeilinger",
  "Lunar New Year": "Manenyttar",
  "Tower of Magic": "Magitarn",
  "Tower of Magic: Impossible": "Magitarn: Umulig",
  "Carnival of Gods": "Gudenes karneval",
  "Mighty Pets": "Mektige kjæledyr",
  "Monster Horde": "Monsterhorde",
  "Large Monster Horde": "Stor monsterhorde",
  "Large Camo Lizard Horde": "Stor kamofirfisle-horde",
  "Large Plantipede Horde": "Stor plantopender-horde",
  "Large Beetloid Horde": "Stor billoid-horde",
  "Medium Monster Horde": "Mellomstor monsterhorde",
  "Medium Camo Lizard Horde": "Mellomstor kamofirfisle-horde",
  "Medium Plantipede Horde": "Mellomstor plantopender-horde",
  "Medium Beetloid Horde": "Mellomstor billoid-horde",
  "Small Monster Horde": "Liten monsterhorde",
  "Small Camo Lizard Horde": "Liten kamofirfisle-horde",
  "Small Plantipede Horde": "Liten plantopender-horde",
  "Small Beetloid Horde": "Liten billoid-horde",
  "Night of the Moth": "Møllens natt",
  "The Brave & The Beautiful": "Den modige og den vakre",
  "Ninja Tower": "Ninjatarn",
  "Ninja Tower: Impossible": "Ninjatarn: Umulig",
  "Secrets of the Opera": "Operaens hemmeligheter",
  "Owl Tower": "Ugletarn",
  "Owl Tower: Impossible": "Ugletarn: Umulig",
  "Find Recruits": "Finn rekrutter",
  "Find Recruits II": "Finn rekrutter II",
  "Scavenge Resources": "Let etter ressurser",
  "Shadows of the Deep": "Dypets skygger",
  "Slayers of Fell Shadows": "Slakterne fra Fell-skyggene",
  "Springvale Festival": "Springvale-festival",
  "Starter Quest": "Startoppdrag",
  "Tower of Styx": "Styx-tarn",
  "Tower of Styx: Impossible": "Styx-tarn: Umulig",
  "The Sand Empire": "Sandriket",
  "Master Barbarian Trials": "Mesterbarbarprøvelser",
  "Master Cleric Trials": "Mesterprestprøvelser",
  "Master Druid Trials": "Mesterdruideprøvelser",
  "Master Fighter Trials": "Mesterslasskjempeprøvelser",
  "Master Monk Trials": "Mestermunkprøvelser",
  "Master Paladin Trials": "Mesterridderprøvelser",
  "Master Ranger Trials": "Mesterskogvokterprøvelser",
  "Master Rogue Trials": "Mestertyvprøvelser",
  "Master Sorcerer Trials": "Mestermagiker-prøvelser",
  "Master Wizard Trials": "Mestertrollmannprøvelser",
  "Contest of Elements": "Elementkonkurransen",
  "Treasure Quest": "Skatteoppdrag",
  "Season of Love": "Kjærlighetens sesong",
  "League of Villains": "Skurkeliga",
  "Save the Winter": "Redd vinteren",
  "Santa's Challenge": "Julenissens utfordring",
  "Gain Experience": "Skaff erfaring",
  "Assist Dragon Mastery": "Hjelpedragemestring",
  "Astral Elves": "Astralalver",
  "Covenant of Champions": "Mesternes pakt",
  "Event Hero Bonus": "Hendelseshelt-bonus",
  "Featured Families": "Fremhevede familier",
  "Hero Roster Mastery": "Mestring av helteliste",
  "Magic Curse": "Magisk forbannelse",
  "Oni Curse": "Oni-forbannelse"
}