{
    "基础技能": "基礎技能",
    "攻击：全体": "攻擊：全體",
    "伤害：持续伤害": "傷害：持續傷害",
    "攻击：单体": "攻擊：單一目標",
    "攻击：两侧": "攻擊：兩側",
    "攻击：范围": "攻擊：範圍",
    "攻击：邻近轻伤": "攻擊：鄰近輕傷",
    "攻击：随机": "攻擊：隨機",
    "攻击：数量变化": "攻擊：數量變化",
    "治疗：复活": "治療：復活",
    "治疗：持续": "治療：持續",
    "治疗：即时": "治療：即時",
    "治疗：伤害量": "治療：傷害量",
    "治疗：提高生命": "治療：提高生命",
    "治疗：特殊": "治療：特殊",
    
    "特殊效果": "特殊效果",
    "攻击-额外攻击": "攻擊-額外攻擊",
    "攻击-回溯/偷取技能": "攻擊-回溯/偷取技能",
    "攻击-连锁": "攻擊-連鎖",
    "攻击-面板：攻击力": "攻擊-面板：攻擊力",
    "攻击-面板：暴击": "攻擊-面板：暴擊",
    "攻击-摧毁小兵": "攻擊-摧毀召喚物",
    "攻击-穿透/绕过": "攻擊-穿透/繞過",
    "攻击-穿透小兵": "攻擊-穿透召喚物",
    "攻击-偷取小兵": "攻擊-偷取召喚物",
    "攻击-无视闪避": "攻擊-無視閃避",
    "攻击-赌博/随机效果": "攻擊-賭博/隨機效果",
    "伤害-额外伤害": "傷害-額外傷害",
    "伤害-爆炸": "傷害-爆炸",
    "伤害-面板：提高伤害": "傷害-面板：提高傷害",
    "伤害-移除小兵造成伤害": "傷害-移除召喚物造成傷害",
    "伤害-伤害↑：暗黑": "傷害-傷害↑：黑暗",
    "伤害-伤害↑：冰霜": "傷害-傷害↑：冰霜",
    "伤害-伤害↑：火焰": "傷害-傷害↑：火焰",
    "伤害-伤害↑：神圣": "傷害-傷害↑：神聖",
    "伤害-伤害↑：自然": "傷害-傷害↑：自然",
    "法力-摧毁小兵获得法力": "法力-摧毀召喚物獲得法力",
    "法力-法力恢复": "法力-法力恢復",
    "法力-法力恢复（击杀）": "法力-法力恢復（擊殺）",
    "法力-法力偷取": "法力-法力奪取",
    "法力-面板：法力生成": "法力-面板：法力生成",
    "法力-削减法力": "法力-削減法力",
    "状态-减少状态异常回合": "狀態-減少狀態異常回合",
    "状态-增益重新分配": "狀態-增益重新分配",
    "状态-偷取增益": "狀態-偷取增益",
    "状态-负面效果重新分配": "狀態-負面效果重新分配",
    "状态-重置负面效果回合": "狀態-重置負面效果回合",
    "状态-重置增益回合": "狀態-重置增益回合",
    "治疗-通过伤害治疗": "治療-透過傷害治療",
    "治疗-通过小兵治疗": "治療-透過召喚物治療",
    "治疗-自我恢复": "治療-自我恢復",
    "召唤-恶魔": "召喚-惡魔",
    "召唤-超级小兵": "召喚-超級召喚物",
    "召唤-超级恶魔": "召喚-超級惡魔",
    "召唤-小兵": "召喚-召喚物",
    "召唤-摧毁恶魔": "召喚-摧毀惡魔",
    
    "增益效果": "增益效果",
    "状态-驱散增益": "狀態-驅散增益",
    "攻击-暴击率↑": "攻擊-暴擊率↑",
    "攻击-成长：攻击力↑": "攻擊-成長：攻擊力↑",
    "攻击-攻击力↑": "攻擊-攻擊力↑",
    "攻击-叠加：攻击力↑": "攻擊-疊加：攻擊力↑",
    "攻击-穿透/绕过": "攻擊-穿透/繞過",
    "法力-法力恢复": "法力-法力恢復",
    "法力-法力生成↑": "法力-法力生成↑",
    "法力-叠加：法力生成↑": "法力-疊加：法力生成↑",
    "防御-反击/反弹": "防禦-反擊/反彈",
    "防御-反击/反弹：暗黑": "防禦-反擊/反彈：黑暗",
    "防御-反击/反弹：火焰": "防禦-反擊/反彈：火焰",
    "防御-反击/反弹：冰霜": "防禦-反擊/反彈：冰霜",
    "防御-反击/反弹：神圣": "防禦-反擊/反彈：神聖",
    "防御-反击/反弹：自然": "防禦-反擊/反彈：自然",
    "攻击-成长：攻击力↑": "防禦-成長：防禦力↑",
    "防御-伤害减免": "防禦-傷害減免",
    "防御-伤害分担": "防禦-傷害分擔",
    "防御-闪避": "防禦-閃避",
    "防御-叠加：防御力↑": "防禦-疊加：防禦力↑",
    "防御-防御↑：暗黑": "防禦-防禦↑：黑暗",
    "防御-防御↑：火焰": "防禦-防禦↑：火焰",
    "防御-防御↑：冰霜": "防禦-防禦↑：冰霜",
    "防御-防御↑：神圣": "防禦-防禦↑：神聖",
    "防御-防御↑：自然": "防禦-防禦↑：自然",
    "防御-防御↑：特殊技能": "防禦-防禦↑：特殊技能",
    "防御-防御力↑": "防禦-防禦力↑",
    "防御-拟态": "防禦-擬態",
    "防御-嘲讽": "防禦-嘲諷",
    "状态-阻止恶魔": "狀態-阻止惡魔",
    "状态-反弹负面效果": "狀態-反彈負面效果",
    "状态-免疫状态异常": "狀態-免疫狀態異常",
    "状态-潜行/幽灵形态": "狀態-躲藏/幽靈形態",
    "状态-替换为增益": "狀態-替換為增益",
    "状态-阻止负面效果": "狀態-阻止負面效果",
    "状态-阻止增益驱散": "狀態-阻止增益驅散",
    "治疗-叠加：生命恢复": "治療-疊加：生命恢復",
    "治疗-治疗量↑": "治療-治療量↑",
    "治疗-自我复活": "治療-自我復活",
    "治疗-自我恢复": "治療-自我恢復",
    "治疗-阻止最大生命值↓": "治療-阻止最大生命值↓",
    
    "负面效果": "負面效果",
    "状态-净化状态异常": "狀態-淨化狀態異常",
    "攻击-攻击力↓": "攻擊-攻擊力↓",
    "攻击-攻击力↓：暗黑": "攻擊-攻擊力↓：黑暗",
    "攻击-命中率↓": "攻擊-命中率↓",
    "攻击-叠加：攻击力↓": "攻擊-疊加：攻擊力↓",
    "攻击-衰退：攻击力↓": "攻擊-枯萎：攻擊力↓",
    "伤害-持续伤害：冰冻": "傷害-持續傷害：霜凍",
    "伤害-持续伤害：燃烧": "傷害-持續傷害：燃燒",
    "伤害-持续伤害：诅咒": "傷害-持續傷害：詛咒",
    "伤害-持续伤害：流血": "傷害-持續傷害：流血",
    "伤害-持续伤害：沙": "傷害-持續傷害：沙",
    "伤害-持续伤害：水": "傷害-持續傷害：水",
    "伤害-持续伤害：毒": "傷害-持續傷害：毒",
    "伤害-持续伤害：生命偷取": "傷害-持續傷害：生命奪取",
    "伤害-叠加：持续伤害": "傷害-疊加：持續傷害",
    "法力-混乱/沉默/睡眠": "法力-混亂/沉默/睡眠",
    "法力-法力偷取": "法力-法力奪取",
    "法力-麻痹": "法力-麻痹",
    "法力-法力生成↓/阻止": "法力-法力生成↓/阻止",
    "法力-叠加：法力生成↓": "法力-疊加：法力生成↓",
    "状态-反弹增益": "狀態-反彈增益",
    "状态-狂乱": "狀態-狂亂",
    "状态-减少增益回合": "狀態-減少增益回合",
    "状态-增益无效化": "狀態-增益無效化",
    "状态-自我减益": "狀態-自我減益",
    "状态-重置负面效果回合": "狀態-重置負面效果回合",
    "状态-阻止净化": "狀態-阻止淨化",
    "状态-阻止小兵": "狀態-阻止召喚物",
    "状态-小兵腐化": "狀態-小兵腐化",
    "状态-吞噬粘物": "狀態-吞噬黏液",
    "状态-天赋技能无效化": "狀態-天賦技能無效化",
    "状态-替换为负面效果": "狀態-替換為負面效果",
    "防御-改变颜色/位置": "防禦-改變顏色/位置",
    "防御-防御↓：暗黑": "防禦-防禦↓：黑暗",
    "防御-防御↓：火焰": "防禦-防禦↓：火焰",
    "防御-防御↓：冰霜": "防禦-防禦↓：冰霜",
    "防御-防御↓：神圣": "防禦-防禦↓：神聖",
    "防御-防御↓：自然": "防禦-防禦↓：自然",
    "防御-防御↓：特殊技能": "防禦-防禦↓：特殊技能",
    "防御-防御力↓": "防禦-防禦力↓",
    "防御-叠加：防御力↓": "防禦-疊加：防禦力↓",
    "防御-叠加：受到伤害↑": "防禦-疊加：受到傷害↑",
    "防御-受到伤害↑": "防禦-受到傷害↑",
    "防御-衰退：防御力↓": "防禦-枯萎：防禦力↓",
    "治疗-最大生命值↓": "治療-最大生命值↓",
    "治疗-治疗量↓": "治療-治療量↓",
    "治疗-阻止复活": "治療-阻止復活",
    "治疗-阻止治疗": "治療-阻止治療",
    "治疗-偷取治疗": "治療-奪取治療"
}